MANIFEST.in
README.md
README.rst
setup.py
wordcounter/__init__.py
wordcounter/wordcounter.py
wordcounter.egg-info/PKG-INFO
wordcounter.egg-info/SOURCES.txt
wordcounter.egg-info/dependency_links.txt
wordcounter.egg-info/top_level.txt
wordcounter/__pycache__/__init__.cpython-36.pyc
wordcounter/__pycache__/wordcounter.cpython-36.pyc