Metadata-Version: 1.1
Name: wordcounter
Version: 0.0.2
Summary: A simple Python module to count words in your given text and many more
Home-page: https://github.com/OmkarPathak/Word-Counter
Author: Omkar Pathak
Author-email: omkarpathak27@gmail.com
License: GPL-2.0
Platform: UNKNOWN
Classifier: Intended Audience :: Developers
Classifier: Topic :: Software Development :: Libraries
Classifier: License :: OSI Approved :: GNU General Public License v2 (GPLv2)
Classifier: Programming Language :: Python :: 2.7
Classifier: Programming Language :: Python :: 3
Classifier: Programming Language :: Python :: 3.3
Classifier: Programming Language :: Python :: 3.4
Classifier: Programming Language :: Python :: 3.5
Classifier: Programming Language :: Python :: 3.6
Classifier: Programming Language :: Python :: 3.7
